<?xml version="1.0" encoding="UTF-8"?>
<DailyXpHighscores>
  <GeneratedAt>1761354000362</GeneratedAt>
  <Player>
    <Rank>1</Rank>
    <Name>Rog</Name>
    <XpEarned>40941698</XpEarned>
  </Player>
  <Player>
    <Rank>2</Rank>
    <Name>Papito</Name>
    <XpEarned>37875836</XpEarned>
  </Player>
  <Player>
    <Rank>3</Rank>
    <Name>Willinha</Name>
    <XpEarned>37215684</XpEarned>
  </Player>
  <Player>
    <Rank>4</Rank>
    <Name>Warr</Name>
    <XpEarned>36631413</XpEarned>
  </Player>
  <Player>
    <Rank>5</Rank>
    <Name>Tiringa</Name>
    <XpEarned>33517773</XpEarned>
  </Player>
  <Player>
    <Rank>6</Rank>
    <Name>Guinny</Name>
    <XpEarned>32695347</XpEarned>
  </Player>
  <Player>
    <Rank>7</Rank>
    <Name>Kinghorrr</Name>
    <XpEarned>31021515</XpEarned>
  </Player>
  <Player>
    <Rank>8</Rank>
    <Name>Alucarde</Name>
    <XpEarned>27947556</XpEarned>
  </Player>
  <Player>
    <Rank>9</Rank>
    <Name>Brokaze</Name>
    <XpEarned>27759036</XpEarned>
  </Player>
  <Player>
    <Rank>10</Rank>
    <Name>Mix</Name>
    <XpEarned>26636439</XpEarned>
  </Player>
  <Player>
    <Rank>11</Rank>
    <Name>Kannisword</Name>
    <XpEarned>25580543</XpEarned>
  </Player>
  <Player>
    <Rank>12</Rank>
    <Name>Patrick </Name>
    <XpEarned>24677463</XpEarned>
  </Player>
  <Player>
    <Rank>13</Rank>
    <Name>Kakarot</Name>
    <XpEarned>24277140</XpEarned>
  </Player>
  <Player>
    <Rank>14</Rank>
    <Name>Hiroshi</Name>
    <XpEarned>23392992</XpEarned>
  </Player>
  <Player>
    <Rank>15</Rank>
    <Name>Srlira</Name>
    <XpEarned>23264588</XpEarned>
  </Player>
  <Player>
    <Rank>16</Rank>
    <Name>Maxx</Name>
    <XpEarned>22009238</XpEarned>
  </Player>
  <Player>
    <Rank>17</Rank>
    <Name>Deadpool</Name>
    <XpEarned>21271426</XpEarned>
  </Player>
  <Player>
    <Rank>18</Rank>
    <Name>Jeeje</Name>
    <XpEarned>20744775</XpEarned>
  </Player>
  <Player>
    <Rank>19</Rank>
    <Name>Xyz</Name>
    <XpEarned>20427951</XpEarned>
  </Player>
  <Player>
    <Rank>20</Rank>
    <Name>Silk</Name>
    <XpEarned>20402874</XpEarned>
  </Player>
  <Player>
    <Rank>21</Rank>
    <Name>Wk</Name>
    <XpEarned>19948698</XpEarned>
  </Player>
  <Player>
    <Rank>22</Rank>
    <Name>Niggawiz</Name>
    <XpEarned>19721726</XpEarned>
  </Player>
  <Player>
    <Rank>23</Rank>
    <Name>Terrifier</Name>
    <XpEarned>19377630</XpEarned>
  </Player>
  <Player>
    <Rank>24</Rank>
    <Name>Juyga</Name>
    <XpEarned>19099037</XpEarned>
  </Player>
  <Player>
    <Rank>25</Rank>
    <Name>Offtank </Name>
    <XpEarned>18397341</XpEarned>
  </Player>
  <Player>
    <Rank>26</Rank>
    <Name>Kannibalz</Name>
    <XpEarned>18026064</XpEarned>
  </Player>
  <Player>
    <Rank>27</Rank>
    <Name>Castiel</Name>
    <XpEarned>17846013</XpEarned>
  </Player>
  <Player>
    <Rank>28</Rank>
    <Name>Kinghor</Name>
    <XpEarned>17105459</XpEarned>
  </Player>
  <Player>
    <Rank>29</Rank>
    <Name>Elizabeht</Name>
    <XpEarned>16372178</XpEarned>
  </Player>
  <Player>
    <Rank>30</Rank>
    <Name>Durau</Name>
    <XpEarned>15411306</XpEarned>
  </Player>
  <Player>
    <Rank>31</Rank>
    <Name>Andis</Name>
    <XpEarned>14035454</XpEarned>
  </Player>
  <Player>
    <Rank>32</Rank>
    <Name>Fakelove</Name>
    <XpEarned>12657203</XpEarned>
  </Player>
  <Player>
    <Rank>33</Rank>
    <Name>Salamaleko</Name>
    <XpEarned>11994948</XpEarned>
  </Player>
  <Player>
    <Rank>34</Rank>
    <Name>Hypersonic</Name>
    <XpEarned>11768083</XpEarned>
  </Player>
  <Player>
    <Rank>35</Rank>
    <Name>Shadowww</Name>
    <XpEarned>11329664</XpEarned>
  </Player>
  <Player>
    <Rank>36</Rank>
    <Name>Michael</Name>
    <XpEarned>11061914</XpEarned>
  </Player>
  <Player>
    <Rank>37</Rank>
    <Name>Devorz</Name>
    <XpEarned>10866586</XpEarned>
  </Player>
  <Player>
    <Rank>38</Rank>
    <Name>Brokazee</Name>
    <XpEarned>10831090</XpEarned>
  </Player>
  <Player>
    <Rank>39</Rank>
    <Name>Novita</Name>
    <XpEarned>10385185</XpEarned>
  </Player>
  <Player>
    <Rank>40</Rank>
    <Name>Panda</Name>
    <XpEarned>10085922</XpEarned>
  </Player>
  <Player>
    <Rank>41</Rank>
    <Name>Olhaeu</Name>
    <XpEarned>9638946</XpEarned>
  </Player>
  <Player>
    <Rank>42</Rank>
    <Name>Opetlak</Name>
    <XpEarned>9353043</XpEarned>
  </Player>
  <Player>
    <Rank>43</Rank>
    <Name>Jalynrabey</Name>
    <XpEarned>8664743</XpEarned>
  </Player>
  <Player>
    <Rank>44</Rank>
    <Name>Mitsuri</Name>
    <XpEarned>8243579</XpEarned>
  </Player>
  <Player>
    <Rank>45</Rank>
    <Name>Hakina</Name>
    <XpEarned>8080842</XpEarned>
  </Player>
  <Player>
    <Rank>46</Rank>
    <Name>Guard</Name>
    <XpEarned>7984226</XpEarned>
  </Player>
  <Player>
    <Rank>47</Rank>
    <Name>Papakill</Name>
    <XpEarned>7839116</XpEarned>
  </Player>
  <Player>
    <Rank>48</Rank>
    <Name>Lught</Name>
    <XpEarned>7558002</XpEarned>
  </Player>
  <Player>
    <Rank>49</Rank>
    <Name>Noobd</Name>
    <XpEarned>7399663</XpEarned>
  </Player>
  <Player>
    <Rank>50</Rank>
    <Name>Hawk</Name>
    <XpEarned>7388525</XpEarned>
  </Player>
  <Player>
    <Rank>51</Rank>
    <Name>Onlymage</Name>
    <XpEarned>6997795</XpEarned>
  </Player>
  <Player>
    <Rank>52</Rank>
    <Name>Xkiritox</Name>
    <XpEarned>6995537</XpEarned>
  </Player>
  <Player>
    <Rank>53</Rank>
    <Name>Coithew</Name>
    <XpEarned>6984068</XpEarned>
  </Player>
  <Player>
    <Rank>54</Rank>
    <Name>Wazzup</Name>
    <XpEarned>6956960</XpEarned>
  </Player>
  <Player>
    <Rank>55</Rank>
    <Name>Tenna</Name>
    <XpEarned>6785609</XpEarned>
  </Player>
  <Player>
    <Rank>56</Rank>
    <Name>Sze</Name>
    <XpEarned>6706221</XpEarned>
  </Player>
  <Player>
    <Rank>57</Rank>
    <Name>Soulviperz</Name>
    <XpEarned>6687844</XpEarned>
  </Player>
  <Player>
    <Rank>58</Rank>
    <Name>Doliki</Name>
    <XpEarned>6259281</XpEarned>
  </Player>
  <Player>
    <Rank>59</Rank>
    <Name>Tingting</Name>
    <XpEarned>6207989</XpEarned>
  </Player>
  <Player>
    <Rank>60</Rank>
    <Name>Konor</Name>
    <XpEarned>6167693</XpEarned>
  </Player>
  <Player>
    <Rank>61</Rank>
    <Name>Senjakala</Name>
    <XpEarned>6149942</XpEarned>
  </Player>
  <Player>
    <Rank>62</Rank>
    <Name>Mochi</Name>
    <XpEarned>5770384</XpEarned>
  </Player>
  <Player>
    <Rank>63</Rank>
    <Name>Lirilai</Name>
    <XpEarned>5625648</XpEarned>
  </Player>
  <Player>
    <Rank>64</Rank>
    <Name>Miau</Name>
    <XpEarned>5457132</XpEarned>
  </Player>
  <Player>
    <Rank>65</Rank>
    <Name>Devorz </Name>
    <XpEarned>5339206</XpEarned>
  </Player>
  <Player>
    <Rank>66</Rank>
    <Name>Hawke</Name>
    <XpEarned>5011524</XpEarned>
  </Player>
  <Player>
    <Rank>67</Rank>
    <Name>Movie</Name>
    <XpEarned>4999243</XpEarned>
  </Player>
  <Player>
    <Rank>68</Rank>
    <Name>Boudicca</Name>
    <XpEarned>4986083</XpEarned>
  </Player>
  <Player>
    <Rank>69</Rank>
    <Name>Sukitaek</Name>
    <XpEarned>4983608</XpEarned>
  </Player>
  <Player>
    <Rank>70</Rank>
    <Name>Jeff</Name>
    <XpEarned>4937737</XpEarned>
  </Player>
  <Player>
    <Rank>71</Rank>
    <Name>Dank</Name>
    <XpEarned>4883069</XpEarned>
  </Player>
  <Player>
    <Rank>72</Rank>
    <Name>Kinghorr</Name>
    <XpEarned>4803435</XpEarned>
  </Player>
  <Player>
    <Rank>73</Rank>
    <Name>Nico</Name>
    <XpEarned>4702320</XpEarned>
  </Player>
  <Player>
    <Rank>74</Rank>
    <Name>Fallen</Name>
    <XpEarned>4671293</XpEarned>
  </Player>
  <Player>
    <Rank>75</Rank>
    <Name>Srsmith</Name>
    <XpEarned>4505409</XpEarned>
  </Player>
  <Player>
    <Rank>76</Rank>
    <Name>Linkun</Name>
    <XpEarned>4502888</XpEarned>
  </Player>
  <Player>
    <Rank>77</Rank>
    <Name>Gta</Name>
    <XpEarned>4466305</XpEarned>
  </Player>
  <Player>
    <Rank>78</Rank>
    <Name>Hypercrab</Name>
    <XpEarned>4424640</XpEarned>
  </Player>
  <Player>
    <Rank>79</Rank>
    <Name>Menson</Name>
    <XpEarned>4380243</XpEarned>
  </Player>
  <Player>
    <Rank>80</Rank>
    <Name>Srasmith</Name>
    <XpEarned>4372878</XpEarned>
  </Player>
  <Player>
    <Rank>81</Rank>
    <Name>Duni</Name>
    <XpEarned>4360632</XpEarned>
  </Player>
  <Player>
    <Rank>82</Rank>
    <Name>Relsing</Name>
    <XpEarned>4328128</XpEarned>
  </Player>
  <Player>
    <Rank>83</Rank>
    <Name>Vegapunk</Name>
    <XpEarned>4320205</XpEarned>
  </Player>
  <Player>
    <Rank>84</Rank>
    <Name>Maddevilz</Name>
    <XpEarned>4244192</XpEarned>
  </Player>
  <Player>
    <Rank>85</Rank>
    <Name>Linzkunz</Name>
    <XpEarned>4238453</XpEarned>
  </Player>
  <Player>
    <Rank>86</Rank>
    <Name>Robin</Name>
    <XpEarned>4174632</XpEarned>
  </Player>
  <Player>
    <Rank>87</Rank>
    <Name>Nibda</Name>
    <XpEarned>4166559</XpEarned>
  </Player>
  <Player>
    <Rank>88</Rank>
    <Name>Vamplod</Name>
    <XpEarned>4155102</XpEarned>
  </Player>
  <Player>
    <Rank>89</Rank>
    <Name>Rara</Name>
    <XpEarned>4131512</XpEarned>
  </Player>
  <Player>
    <Rank>90</Rank>
    <Name>Nigata</Name>
    <XpEarned>4083534</XpEarned>
  </Player>
  <Player>
    <Rank>91</Rank>
    <Name>Zennitsu</Name>
    <XpEarned>4079342</XpEarned>
  </Player>
  <Player>
    <Rank>92</Rank>
    <Name>Pcyann</Name>
    <XpEarned>4046017</XpEarned>
  </Player>
  <Player>
    <Rank>93</Rank>
    <Name>Neruru</Name>
    <XpEarned>3978780</XpEarned>
  </Player>
  <Player>
    <Rank>94</Rank>
    <Name>Gint</Name>
    <XpEarned>3928782</XpEarned>
  </Player>
  <Player>
    <Rank>95</Rank>
    <Name>Xkiritoxwi</Name>
    <XpEarned>3885525</XpEarned>
  </Player>
  <Player>
    <Rank>96</Rank>
    <Name>Scarlet</Name>
    <XpEarned>3799960</XpEarned>
  </Player>
  <Player>
    <Rank>97</Rank>
    <Name>Lendario</Name>
    <XpEarned>3792381</XpEarned>
  </Player>
  <Player>
    <Rank>98</Rank>
    <Name>Mord</Name>
    <XpEarned>3738223</XpEarned>
  </Player>
  <Player>
    <Rank>99</Rank>
    <Name>Hawkeyez</Name>
    <XpEarned>3703140</XpEarned>
  </Player>
  <Player>
    <Rank>100</Rank>
    <Name>Sandman</Name>
    <XpEarned>3682853</XpEarned>
  </Player>
  <Player>
    <Rank>101</Rank>
    <Name>Apish</Name>
    <XpEarned>3492446</XpEarned>
  </Player>
  <Player>
    <Rank>102</Rank>
    <Name>Costa</Name>
    <XpEarned>3423302</XpEarned>
  </Player>
  <Player>
    <Rank>103</Rank>
    <Name>Titania</Name>
    <XpEarned>3376152</XpEarned>
  </Player>
  <Player>
    <Rank>104</Rank>
    <Name>Mineira</Name>
    <XpEarned>3342199</XpEarned>
  </Player>
  <Player>
    <Rank>105</Rank>
    <Name>Tiosukita</Name>
    <XpEarned>3332984</XpEarned>
  </Player>
  <Player>
    <Rank>106</Rank>
    <Name>Galacticos</Name>
    <XpEarned>3321076</XpEarned>
  </Player>
  <Player>
    <Rank>107</Rank>
    <Name>Ares</Name>
    <XpEarned>3311483</XpEarned>
  </Player>
  <Player>
    <Rank>108</Rank>
    <Name>Poderosa </Name>
    <XpEarned>3304360</XpEarned>
  </Player>
  <Player>
    <Rank>109</Rank>
    <Name>Menon</Name>
    <XpEarned>3268776</XpEarned>
  </Player>
  <Player>
    <Rank>110</Rank>
    <Name>Mane</Name>
    <XpEarned>3261620</XpEarned>
  </Player>
  <Player>
    <Rank>111</Rank>
    <Name>Akane</Name>
    <XpEarned>3238625</XpEarned>
  </Player>
  <Player>
    <Rank>112</Rank>
    <Name>Hawkk</Name>
    <XpEarned>3226860</XpEarned>
  </Player>
  <Player>
    <Rank>113</Rank>
    <Name>Nemo</Name>
    <XpEarned>3191946</XpEarned>
  </Player>
  <Player>
    <Rank>114</Rank>
    <Name>Nide</Name>
    <XpEarned>3158045</XpEarned>
  </Player>
  <Player>
    <Rank>115</Rank>
    <Name>Kaos</Name>
    <XpEarned>3119853</XpEarned>
  </Player>
  <Player>
    <Rank>116</Rank>
    <Name>Maxz</Name>
    <XpEarned>3072718</XpEarned>
  </Player>
  <Player>
    <Rank>117</Rank>
    <Name>Maah</Name>
    <XpEarned>3022230</XpEarned>
  </Player>
  <Player>
    <Rank>118</Rank>
    <Name>Wizloko</Name>
    <XpEarned>2913994</XpEarned>
  </Player>
  <Player>
    <Rank>119</Rank>
    <Name>Feiticeira</Name>
    <XpEarned>2797390</XpEarned>
  </Player>
  <Player>
    <Rank>120</Rank>
    <Name>Erthep</Name>
    <XpEarned>2762032</XpEarned>
  </Player>
  <Player>
    <Rank>121</Rank>
    <Name>Nudin</Name>
    <XpEarned>2688581</XpEarned>
  </Player>
  <Player>
    <Rank>122</Rank>
    <Name>Dodo</Name>
    <XpEarned>2638946</XpEarned>
  </Player>
  <Player>
    <Rank>123</Rank>
    <Name>Vingky</Name>
    <XpEarned>2536550</XpEarned>
  </Player>
  <Player>
    <Rank>124</Rank>
    <Name>Excalibur</Name>
    <XpEarned>2500941</XpEarned>
  </Player>
  <Player>
    <Rank>125</Rank>
    <Name>Liaauliaa</Name>
    <XpEarned>2481810</XpEarned>
  </Player>
  <Player>
    <Rank>126</Rank>
    <Name>Anfasa</Name>
    <XpEarned>2422081</XpEarned>
  </Player>
  <Player>
    <Rank>127</Rank>
    <Name>Odda</Name>
    <XpEarned>2419936</XpEarned>
  </Player>
  <Player>
    <Rank>128</Rank>
    <Name>Datokziqri</Name>
    <XpEarned>2253191</XpEarned>
  </Player>
  <Player>
    <Rank>129</Rank>
    <Name>Namfone</Name>
    <XpEarned>2246112</XpEarned>
  </Player>
  <Player>
    <Rank>130</Rank>
    <Name>Mago</Name>
    <XpEarned>2236466</XpEarned>
  </Player>
  <Player>
    <Rank>131</Rank>
    <Name>Ragnarsz</Name>
    <XpEarned>2230387</XpEarned>
  </Player>
  <Player>
    <Rank>132</Rank>
    <Name>Superhero</Name>
    <XpEarned>2207225</XpEarned>
  </Player>
  <Player>
    <Rank>133</Rank>
    <Name>Wiz</Name>
    <XpEarned>2155559</XpEarned>
  </Player>
  <Player>
    <Rank>134</Rank>
    <Name>Evelynn</Name>
    <XpEarned>2125545</XpEarned>
  </Player>
  <Player>
    <Rank>135</Rank>
    <Name>Rexag</Name>
    <XpEarned>2095912</XpEarned>
  </Player>
  <Player>
    <Rank>136</Rank>
    <Name>Luskridys</Name>
    <XpEarned>2019143</XpEarned>
  </Player>
  <Player>
    <Rank>137</Rank>
    <Name>Rexeg</Name>
    <XpEarned>1994477</XpEarned>
  </Player>
  <Player>
    <Rank>138</Rank>
    <Name>Gibranx</Name>
    <XpEarned>1898235</XpEarned>
  </Player>
  <Player>
    <Rank>139</Rank>
    <Name>Warbr </Name>
    <XpEarned>1896933</XpEarned>
  </Player>
  <Player>
    <Rank>140</Rank>
    <Name>Zecaurubu</Name>
    <XpEarned>1787576</XpEarned>
  </Player>
  <Player>
    <Rank>141</Rank>
    <Name>Myrden</Name>
    <XpEarned>1717630</XpEarned>
  </Player>
  <Player>
    <Rank>142</Rank>
    <Name>Dblack</Name>
    <XpEarned>1683494</XpEarned>
  </Player>
  <Player>
    <Rank>143</Rank>
    <Name>Kafka</Name>
    <XpEarned>1672420</XpEarned>
  </Player>
  <Player>
    <Rank>144</Rank>
    <Name>Eunha</Name>
    <XpEarned>1622150</XpEarned>
  </Player>
  <Player>
    <Rank>145</Rank>
    <Name>Nadibelly</Name>
    <XpEarned>1599452</XpEarned>
  </Player>
  <Player>
    <Rank>146</Rank>
    <Name>Rono</Name>
    <XpEarned>1575000</XpEarned>
  </Player>
  <Player>
    <Rank>147</Rank>
    <Name>Sariel</Name>
    <XpEarned>1575000</XpEarned>
  </Player>
  <Player>
    <Rank>148</Rank>
    <Name>Jockey</Name>
    <XpEarned>1575000</XpEarned>
  </Player>
  <Player>
    <Rank>149</Rank>
    <Name>Costaup</Name>
    <XpEarned>1575000</XpEarned>
  </Player>
  <Player>
    <Rank>150</Rank>
    <Name>Doflamingu</Name>
    <XpEarned>1575000</XpEarned>
  </Player>
  <Player>
    <Rank>151</Rank>
    <Name>Rena</Name>
    <XpEarned>1531202</XpEarned>
  </Player>
  <Player>
    <Rank>152</Rank>
    <Name>Charuto</Name>
    <XpEarned>1366213</XpEarned>
  </Player>
  <Player>
    <Rank>153</Rank>
    <Name>Orgr</Name>
    <XpEarned>1334951</XpEarned>
  </Player>
  <Player>
    <Rank>154</Rank>
    <Name>Bruxo</Name>
    <XpEarned>1317016</XpEarned>
  </Player>
  <Player>
    <Rank>155</Rank>
    <Name>Xmatthew</Name>
    <XpEarned>1301782</XpEarned>
  </Player>
  <Player>
    <Rank>156</Rank>
    <Name>Heetee</Name>
    <XpEarned>1266332</XpEarned>
  </Player>
  <Player>
    <Rank>157</Rank>
    <Name>Cursed</Name>
    <XpEarned>1241092</XpEarned>
  </Player>
  <Player>
    <Rank>158</Rank>
    <Name>Yena</Name>
    <XpEarned>1227832</XpEarned>
  </Player>
  <Player>
    <Rank>159</Rank>
    <Name>Loan</Name>
    <XpEarned>1142561</XpEarned>
  </Player>
  <Player>
    <Rank>160</Rank>
    <Name>Singsing</Name>
    <XpEarned>1114041</XpEarned>
  </Player>
  <Player>
    <Rank>161</Rank>
    <Name>Scott </Name>
    <XpEarned>1086634</XpEarned>
  </Player>
  <Player>
    <Rank>162</Rank>
    <Name>Sukarno</Name>
    <XpEarned>1064706</XpEarned>
  </Player>
  <Player>
    <Rank>163</Rank>
    <Name>Tiao</Name>
    <XpEarned>1060877</XpEarned>
  </Player>
  <Player>
    <Rank>164</Rank>
    <Name>Gryffindor</Name>
    <XpEarned>1050000</XpEarned>
  </Player>
  <Player>
    <Rank>165</Rank>
    <Name>Anindya</Name>
    <XpEarned>1050000</XpEarned>
  </Player>
  <Player>
    <Rank>166</Rank>
    <Name>Guinness </Name>
    <XpEarned>1050000</XpEarned>
  </Player>
  <Player>
    <Rank>167</Rank>
    <Name>Thecrot</Name>
    <XpEarned>1007881</XpEarned>
  </Player>
  <Player>
    <Rank>168</Rank>
    <Name>Bigbig</Name>
    <XpEarned>999415</XpEarned>
  </Player>
  <Player>
    <Rank>169</Rank>
    <Name>Morgana</Name>
    <XpEarned>891439</XpEarned>
  </Player>
  <Player>
    <Rank>170</Rank>
    <Name>Anfasaaa</Name>
    <XpEarned>839103</XpEarned>
  </Player>
  <Player>
    <Rank>171</Rank>
    <Name>Weedking</Name>
    <XpEarned>836103</XpEarned>
  </Player>
  <Player>
    <Rank>172</Rank>
    <Name>Jminh</Name>
    <XpEarned>834942</XpEarned>
  </Player>
  <Player>
    <Rank>173</Rank>
    <Name>Prylak</Name>
    <XpEarned>767312</XpEarned>
  </Player>
  <Player>
    <Rank>174</Rank>
    <Name>Daledere</Name>
    <XpEarned>758733</XpEarned>
  </Player>
  <Player>
    <Rank>175</Rank>
    <Name>Ahrifox </Name>
    <XpEarned>723652</XpEarned>
  </Player>
  <Player>
    <Rank>176</Rank>
    <Name>Aivk</Name>
    <XpEarned>691518</XpEarned>
  </Player>
  <Player>
    <Rank>177</Rank>
    <Name>Babywar</Name>
    <XpEarned>688674</XpEarned>
  </Player>
  <Player>
    <Rank>178</Rank>
    <Name>Psychology</Name>
    <XpEarned>684174</XpEarned>
  </Player>
  <Player>
    <Rank>179</Rank>
    <Name>Ceifeiro</Name>
    <XpEarned>624070</XpEarned>
  </Player>
  <Player>
    <Rank>180</Rank>
    <Name>Ninalaro</Name>
    <XpEarned>612996</XpEarned>
  </Player>
  <Player>
    <Rank>181</Rank>
    <Name>Bounpone</Name>
    <XpEarned>600418</XpEarned>
  </Player>
  <Player>
    <Rank>182</Rank>
    <Name>Khalamel</Name>
    <XpEarned>600245</XpEarned>
  </Player>
  <Player>
    <Rank>183</Rank>
    <Name>Rafe</Name>
    <XpEarned>559010</XpEarned>
  </Player>
  <Player>
    <Rank>184</Rank>
    <Name>Anakbaik</Name>
    <XpEarned>558825</XpEarned>
  </Player>
  <Player>
    <Rank>185</Rank>
    <Name>Prylek</Name>
    <XpEarned>553862</XpEarned>
  </Player>
  <Player>
    <Rank>186</Rank>
    <Name>Nex</Name>
    <XpEarned>552064</XpEarned>
  </Player>
  <Player>
    <Rank>187</Rank>
    <Name>Scott</Name>
    <XpEarned>525000</XpEarned>
  </Player>
  <Player>
    <Rank>188</Rank>
    <Name>Luluzinha</Name>
    <XpEarned>500868</XpEarned>
  </Player>
  <Player>
    <Rank>189</Rank>
    <Name>Nulonebi</Name>
    <XpEarned>485036</XpEarned>
  </Player>
  <Player>
    <Rank>190</Rank>
    <Name>Powerofgod</Name>
    <XpEarned>420672</XpEarned>
  </Player>
  <Player>
    <Rank>191</Rank>
    <Name>Jupiiter</Name>
    <XpEarned>416282</XpEarned>
  </Player>
  <Player>
    <Rank>192</Rank>
    <Name>Zms</Name>
    <XpEarned>343784</XpEarned>
  </Player>
  <Player>
    <Rank>193</Rank>
    <Name>Tuanmuda</Name>
    <XpEarned>321332</XpEarned>
  </Player>
  <Player>
    <Rank>194</Rank>
    <Name>Thunderx</Name>
    <XpEarned>319095</XpEarned>
  </Player>
  <Player>
    <Rank>195</Rank>
    <Name>Ola</Name>
    <XpEarned>313008</XpEarned>
  </Player>
  <Player>
    <Rank>196</Rank>
    <Name>Naxu</Name>
    <XpEarned>279235</XpEarned>
  </Player>
  <Player>
    <Rank>197</Rank>
    <Name>Valenca</Name>
    <XpEarned>263228</XpEarned>
  </Player>
  <Player>
    <Rank>198</Rank>
    <Name>Plover</Name>
    <XpEarned>261895</XpEarned>
  </Player>
  <Player>
    <Rank>199</Rank>
    <Name>Kingwarr</Name>
    <XpEarned>249480</XpEarned>
  </Player>
  <Player>
    <Rank>200</Rank>
    <Name>Lievian</Name>
    <XpEarned>243306</XpEarned>
  </Player>
  <Player>
    <Rank>201</Rank>
    <Name>Khrisna</Name>
    <XpEarned>217875</XpEarned>
  </Player>
  <Player>
    <Rank>202</Rank>
    <Name>Cilaka</Name>
    <XpEarned>216259</XpEarned>
  </Player>
  <Player>
    <Rank>203</Rank>
    <Name>Hellooo</Name>
    <XpEarned>212546</XpEarned>
  </Player>
  <Player>
    <Rank>204</Rank>
    <Name>Oliviaa</Name>
    <XpEarned>187768</XpEarned>
  </Player>
  <Player>
    <Rank>205</Rank>
    <Name>Zilong</Name>
    <XpEarned>134103</XpEarned>
  </Player>
  <Player>
    <Rank>206</Rank>
    <Name>Luci</Name>
    <XpEarned>131768</XpEarned>
  </Player>
  <Player>
    <Rank>207</Rank>
    <Name>Chivas</Name>
    <XpEarned>130900</XpEarned>
  </Player>
  <Player>
    <Rank>208</Rank>
    <Name>Makaveli</Name>
    <XpEarned>114152</XpEarned>
  </Player>
  <Player>
    <Rank>209</Rank>
    <Name>Torchlight</Name>
    <XpEarned>109594</XpEarned>
  </Player>
  <Player>
    <Rank>210</Rank>
    <Name>Dubaii</Name>
    <XpEarned>101150</XpEarned>
  </Player>
  <Player>
    <Rank>211</Rank>
    <Name>Sanchai</Name>
    <XpEarned>99960</XpEarned>
  </Player>
  <Player>
    <Rank>212</Rank>
    <Name>Thc</Name>
    <XpEarned>80920</XpEarned>
  </Player>
  <Player>
    <Rank>213</Rank>
    <Name>Himurra</Name>
    <XpEarned>79764</XpEarned>
  </Player>
  <Player>
    <Rank>214</Rank>
    <Name>Steve</Name>
    <XpEarned>71400</XpEarned>
  </Player>
  <Player>
    <Rank>215</Rank>
    <Name>Abdul</Name>
    <XpEarned>69868</XpEarned>
  </Player>
  <Player>
    <Rank>216</Rank>
    <Name>Tora</Name>
    <XpEarned>47780</XpEarned>
  </Player>
  <Player>
    <Rank>217</Rank>
    <Name>Libi</Name>
    <XpEarned>42169</XpEarned>
  </Player>
  <Player>
    <Rank>218</Rank>
    <Name>Renansz</Name>
    <XpEarned>42000</XpEarned>
  </Player>
  <Player>
    <Rank>219</Rank>
    <Name>Cochilo</Name>
    <XpEarned>41580</XpEarned>
  </Player>
  <Player>
    <Rank>220</Rank>
    <Name>Kresley</Name>
    <XpEarned>39009</XpEarned>
  </Player>
  <Player>
    <Rank>221</Rank>
    <Name>Nou</Name>
    <XpEarned>31220</XpEarned>
  </Player>
  <Player>
    <Rank>222</Rank>
    <Name>Kooo</Name>
    <XpEarned>28861</XpEarned>
  </Player>
  <Player>
    <Rank>223</Rank>
    <Name>Harley</Name>
    <XpEarned>23503</XpEarned>
  </Player>
  <Player>
    <Rank>224</Rank>
    <Name>Hallan</Name>
    <XpEarned>19992</XpEarned>
  </Player>
  <Player>
    <Rank>225</Rank>
    <Name>Playback</Name>
    <XpEarned>16692</XpEarned>
  </Player>
  <Player>
    <Rank>226</Rank>
    <Name>Lovess</Name>
    <XpEarned>16184</XpEarned>
  </Player>
  <Player>
    <Rank>227</Rank>
    <Name>Immortal</Name>
    <XpEarned>2206</XpEarned>
  </Player>
  <Player>
    <Rank>228</Rank>
    <Name>Miragem</Name>
    <XpEarned>714</XpEarned>
  </Player>
  <Player>
    <Rank>229</Rank>
    <Name>Alicelu</Name>
    <XpEarned>623</XpEarned>
  </Player>
  <Player>
    <Rank>230</Rank>
    <Name>Abgkumis</Name>
    <XpEarned>154</XpEarned>
  </Player>
  <Player>
    <Rank>231</Rank>
    <Name>Megume</Name>
    <XpEarned>140</XpEarned>
  </Player>
  <Player>
    <Rank>232</Rank>
    <Name>Oole</Name>
    <XpEarned>0</XpEarned>
  </Player>
  <Player>
    <Rank>233</Rank>
    <Name>Veronica </Name>
    <XpEarned>0</XpEarned>
  </Player>
  <Player>
    <Rank>234</Rank>
    <Name>Babywiz</Name>
    <XpEarned>0</XpEarned>
  </Player>
  <Player>
    <Rank>235</Rank>
    <Name>Yozo</Name>
    <XpEarned>0</XpEarned>
  </Player>
  <Player>
    <Rank>236</Rank>
    <Name>Yulala</Name>
    <XpEarned>0</XpEarned>
  </Player>
  <Player>
    <Rank>237</Rank>
    <Name>Nightmare</Name>
    <XpEarned>0</XpEarned>
  </Player>
  <Player>
    <Rank>238</Rank>
    <Name>Artemis</Name>
    <XpEarned>0</XpEarned>
  </Player>
  <Player>
    <Rank>239</Rank>
    <Name>Bala</Name>
    <XpEarned>0</XpEarned>
  </Player>
  <Player>
    <Rank>240</Rank>
    <Name>Omadara</Name>
    <XpEarned>0</XpEarned>
  </Player>
  <Player>
    <Rank>241</Rank>
    <Name>Lederoni</Name>
    <XpEarned>-79024</XpEarned>
  </Player>
  <Player>
    <Rank>242</Rank>
    <Name>Vanssbooot</Name>
    <XpEarned>-170974</XpEarned>
  </Player>
  <Player>
    <Rank>243</Rank>
    <Name>Pesadelo </Name>
    <XpEarned>-13794013</XpEarned>
  </Player>
</DailyXpHighscores>
